tavily_mcp_server/__init__.py
tavily_mcp_server/server.py
tavily_mcp_server-1.1.3.dist-info/licenses/LICENSE
tavily_mcp_server-1.1.3.dist-info/METADATA
tavily_mcp_server-1.1.3.dist-info/WHEEL
tavily_mcp_server-1.1.3.dist-info/entry_points.txt
tavily_mcp_server-1.1.3.dist-info/top_level.txt
tavily_mcp_server-1.1.3.dist-info/RECORD
