Metadata-Version: 2.4
Name: tavily-mcp-server
Version: 1.1.3
Summary: Tavily搜索MCP服务智能体 - 为AI智能体提供强大的网络搜索能力
Home-page: https://github.com/mcp-team/tavily-mcp-server
Author: MCP Team
Author-email: MCP Team <support@mcp.dev>
License: MIT
Project-URL: Homepage, https://github.com/mcp-team/tavily-mcp-server
Project-URL: Repository, https://github.com/mcp-team/tavily-mcp-server
Project-URL: Documentation, https://github.com/mcp-team/tavily-mcp-server#readme
Project-URL: Bug Tracker, https://github.com/mcp-team/tavily-mcp-server/issues
Keywords: tavily,search,mcp,ai,agent,fastapi,web-search
Classifier: Development Status :: 4 - Beta
Classifier: Intended Audience :: Developers
Classifier: License :: OSI Approved :: MIT License
Classifier: Programming Language :: Python :: 3
Classifier: Programming Language :: Python :: 3.8
Classifier: Programming Language :: Python :: 3.9
Classifier: Programming Language :: Python :: 3.10
Classifier: Programming Language :: Python :: 3.11
Classifier: Programming Language :: Python :: 3.12
Classifier: Topic :: Internet :: WWW/HTTP :: Indexing/Search
Classifier: Topic :: Software Development :: Libraries :: Python Modules
Classifier: Topic :: Scientific/Engineering :: Artificial Intelligence
Requires-Python: >=3.8
License-File: LICENSE
Requires-Dist: fastapi>=0.68.0
Requires-Dist: uvicorn[standard]>=0.15.0
Requires-Dist: python-dotenv>=0.19.0
Requires-Dist: tavily-python>=0.1.3
Requires-Dist: fastmcp>=0.1.0
Requires-Dist: pydantic>=2.0.0
Provides-Extra: dev
Requires-Dist: pytest>=6.0; extra == "dev"
Requires-Dist: pytest-asyncio>=0.18.0; extra == "dev"
Requires-Dist: black>=22.0; extra == "dev"
Requires-Dist: flake8>=4.0; extra == "dev"
Requires-Dist: mypy>=0.950; extra == "dev"
Dynamic: author
Dynamic: home-page
Dynamic: license-file
Dynamic: requires-python
